Metadata-Version: 1.0
Name: Qtickle
Version: 1.5.9
Summary: 
Home-page: https://github.com/tisaconundrum2/Qtickle
Author: Nicholas Finch
Author-email: tisaconundrum2@github.com
License: UNKNOWN
Platform: UNKNOWN
